__init__.py
__main__.py
time_until.py
time_until-0.1.3.dist-info/LICENSE
time_until-0.1.3.dist-info/METADATA
time_until-0.1.3.dist-info/WHEEL
time_until-0.1.3.dist-info/entry_points.txt
time_until-0.1.3.dist-info/top_level.txt
time_until-0.1.3.dist-info/RECORD
