Metadata-Version: 2.1
Name: time_until
Version: 0.1.3
Summary: Application that calculate time duration until reach a given date
Author-email: Thiago Jacinto <46906069+thiagojacinto@users.noreply.github.com>
Project-URL: Homepage, https://github.com/thiagojacinto/time-until-cli
Project-URL: Bug Tracker, https://github.com/thiagojacinto/time-until-cli/issues
Project-URL: General Discussions, https://github.com/thiagojacinto/time-until-cli/discussions
Classifier: Programming Language :: Python :: 3
Classifier: License :: OSI Approved :: GNU General Public License v3 (GPLv3)
Classifier: Operating System :: OS Independent
Classifier: Development Status :: 5 - Production/Stable
Requires-Python: >=3.10.15
License-File: LICENSE
Requires-Dist: attrs ==24.2.0
Requires-Dist: click ==8.1.3
Requires-Dist: colorama ==0.4.6
Requires-Dist: commonmark ==0.9.1
Requires-Dist: exceptiongroup ==1.1.0
Requires-Dist: iniconfig ==2.0.0
Requires-Dist: packaging ==24.1
Requires-Dist: pluggy ==1.0.0
Requires-Dist: Pygments ==2.14.0
Requires-Dist: python-dateutil ==2.8.2
Requires-Dist: rich ==13.9.4
Requires-Dist: shellingham ==1.5.0.post1
Requires-Dist: six ==1.16.0
Requires-Dist: tomli ==2.0.1
Requires-Dist: typer ==0.7.0
